tinyimage/__init__.py
tinyimage/img_obj.py
tinyimage/tools.py
tinyimage-0.0.5.dist-info/LICENSE
tinyimage-0.0.5.dist-info/METADATA
tinyimage-0.0.5.dist-info/WHEEL
tinyimage-0.0.5.dist-info/top_level.txt
tinyimage-0.0.5.dist-info/RECORD
