Metadata-Version: 2.1
Name: tinyimage
Version: 0.0.5
Summary: a lightweight image object library
Home-page: https://github.com/VisualDataIO/tinyimage
Author: Jie Feng
Author-email: jiefeng@perceptance.io
License: UNKNOWN
Keywords: computer vision image
Platform: UNKNOWN
Requires-Dist: pillow
Requires-Dist: numpy
Requires-Dist: opencv-python
